<annotation>
	<folder>train</folder>
	<filename>C25.jpg</filename>
	<path>/home/gunjan/Desktop/card_images/train/C25.jpg</path>
	<source>
		<database>Unknown</database>
	</source>
	<size>
		<width>186</width>
		<height>271</height>
		<depth>3</depth>
	</size>
	<segmented>0</segmented>
	<object>
		<name>two of clubs</name>
		<pose>Unspecified</pose>
		<truncated>0</truncated>
		<difficult>0</difficult>
		<bndbox>
			<xmin>10</xmin>
			<ymin>10</ymin>
			<xmax>176</xmax>
			<ymax>245</ymax>
		</bndbox>
	</object>
</annotation>
