<annotation>
	<folder>train</folder>
	<filename>d65.jpg</filename>
	<path>/home/gunjan/Desktop/card_images/train/d65.jpg</path>
	<source>
		<database>Unknown</database>
	</source>
	<size>
		<width>180</width>
		<height>280</height>
		<depth>3</depth>
	</size>
	<segmented>0</segmented>
	<object>
		<name>six of diamonds</name>
		<pose>Unspecified</pose>
		<truncated>0</truncated>
		<difficult>0</difficult>
		<bndbox>
			<xmin>13</xmin>
			<ymin>13</ymin>
			<xmax>167</xmax>
			<ymax>247</ymax>
		</bndbox>
	</object>
</annotation>
